hubify_dataset-0.1.4.dist-info/licenses/LICENSE
src/__init__.py
src/main.py
src/utils.py
hubify_dataset-0.1.4.dist-info/METADATA
hubify_dataset-0.1.4.dist-info/WHEEL
hubify_dataset-0.1.4.dist-info/entry_points.txt
hubify_dataset-0.1.4.dist-info/top_level.txt
hubify_dataset-0.1.4.dist-info/RECORD
