Metadata-Version: 2.4
Name: hubify-dataset
Version: 0.1.4
Summary: Convert object detection datasets (COCO, YOLO, Pascal VOC, etc.) to HuggingFace format
Requires-Python: >=3.10
License-File: LICENSE
Requires-Dist: datasets>=4.4.2
Requires-Dist: huggingface-hub>=1.2.3
Requires-Dist: pillow>=12.1.0
Requires-Dist: pyyaml>=6.0
Requires-Dist: rich>=13.9.4
Provides-Extra: dev
Requires-Dist: ruff>=0.14.10; extra == "dev"
Dynamic: license-file
